mozdef_util/__init__.py
mozdef_util/bulk_queue.py
mozdef_util/elasticsearch_client.py
mozdef_util/event.py
mozdef_util/geo_ip.py
mozdef_util/plugin_set.py
mozdef_util/state.py
mozdef_util/query_models/__init__.py
mozdef_util/query_models/aggregated_results.py
mozdef_util/query_models/aggregation.py
mozdef_util/query_models/boolean_match.py
mozdef_util/query_models/exists_match.py
mozdef_util/query_models/less_than_match.py
mozdef_util/query_models/phrase_match.py
mozdef_util/query_models/query_string_match.py
mozdef_util/query_models/range_match.py
mozdef_util/query_models/search_query.py
mozdef_util/query_models/simple_results.py
mozdef_util/query_models/subnet_match.py
mozdef_util/query_models/term_match.py
mozdef_util/query_models/terms_match.py
mozdef_util/query_models/wildcard_match.py
mozdef_util/utilities/__init__.py
mozdef_util/utilities/dict2List.py
mozdef_util/utilities/dot_dict.py
mozdef_util/utilities/is_cef.py
mozdef_util/utilities/is_ip.py
mozdef_util/utilities/key_exists.py
mozdef_util/utilities/logger.py
mozdef_util/utilities/remove_at.py
mozdef_util/utilities/toUTC.py
mozdef_util/utilities/to_unicode.py
mozdef_util-3.0.7.dist-info/LICENSE
mozdef_util-3.0.7.dist-info/METADATA
mozdef_util-3.0.7.dist-info/WHEEL
mozdef_util-3.0.7.dist-info/top_level.txt
mozdef_util-3.0.7.dist-info/RECORD
